{
    "criteria": {
        "requirement": {
            "trigger": "minecraft:default_block_use",
            "conditions": {
                "location": [
                    {
                        "condition": "minecraft:location_check",
                        "predicate": {
                            "block": {
                                "blocks": "minecraft:barrel",
                                "predicates": {
                                    "minecraft:custom_data": {
                                        "jabkacore.recipes": true
                                    }
                                }
                            }
                        }
                    }
                ]
            }
        }
    },
    "rewards": {
        "function": "jabkacore:internal/recipes/open"
    }
}